pyrk/__init__.py
pyrk/pyrk.py
pyrk-2023.11.9.dist-info/METADATA
pyrk-2023.11.9.dist-info/WHEEL
pyrk-2023.11.9.dist-info/RECORD
