Metadata-Version: 2.1
Name: pyrk
Version: 2023.11.9
Summary: ode integration rk4 rk runge kutta
Home-page: https://pypi.org/project/pyrk/
License: MIT
Keywords: ode,rk4,runge,kutta
Author: walchko
Author-email: walchko@users.noreply.github.com
Requires-Python: >=3.8
Classifier: Development Status :: 4 - Beta
Classifier: Intended Audience :: Developers
Classifier: License :: OSI Approved :: MIT License
Classifier: Operating System :: OS Independent
Classifier: Programming Language :: Python :: 3
Classifier: Programming Language :: Python :: 3.8
Classifier: Programming Language :: Python :: 3.9
Classifier: Programming Language :: Python :: 3.10
Classifier: Programming Language :: Python :: 3.11
Classifier: Topic :: Software Development :: Libraries
Classifier: Topic :: Software Development :: Libraries :: Application Frameworks
Classifier: Topic :: Software Development :: Libraries :: Python Modules
Project-URL: Repository, https://github.com/walchko/pyrk
